pyDARTLAB/__init__.py
pyDARTLAB/dartlabplot.py
pyDARTLAB/increments.py
pyDARTLAB/lorenz_96.py
pyDARTLAB/oned_ensemble.py
pyDARTLAB/twod_ensemble.py
pydartlab-0.0.1.dist-info/METADATA
pydartlab-0.0.1.dist-info/WHEEL
pydartlab-0.0.1.dist-info/licenses/LICENSE
pydartlab-0.0.1.dist-info/RECORD
