Metadata-Version: 2.3
Name: pydartlab
Version: 0.0.1
Summary: A python version of DARTLAB
Project-URL: Homepage, https://github.com/NCAR/pyDARTLAB
Project-URL: Issues, https://github.com/NCAR/pyDARTLAB/issues
Author-email: Helen Kershaw <hkershaw@ucar.edu>
License-File: LICENSE
Classifier: License :: OSI Approved :: Apache Software License
Classifier: Operating System :: OS Independent
Classifier: Programming Language :: Python :: 3
Requires-Python: >=3.8
Requires-Dist: matplotlib==3.9.1
